solarsystemMB/SSObject.py
solarsystemMB/__init__.py
solarsystemMB/initialize_SolarSystem_db.py
solarsystemMB/load_kernels.py
solarsystemMB/planet_dist.py
solarsystemMB/planet_geometry.py
solarsystemMB/relative_position.py
solarsystemMB/version.py
solarsystemMB/data/PlanetaryConstants.dat
solarsystemMB/data/naif_ids.dat
solarsystemMB/data/sso_query.sql
solarsystemMB-1.1.6.dist-info/LICENSE.rst
solarsystemMB-1.1.6.dist-info/METADATA
solarsystemMB-1.1.6.dist-info/WHEEL
solarsystemMB-1.1.6.dist-info/top_level.txt
solarsystemMB-1.1.6.dist-info/RECORD
