Metadata-Version: 2.1
Name: solarsystemMB
Version: 1.1.6
Summary: Solar System procedures for nexoclom and general use
Home-page: https://github.com/mburger-stsci/solarsystemMB
Author: Matthew Burger
Author-email: mburger@stsci.edu
License: BSD 3-Clause
Platform: UNKNOWN
Requires-Python: >=3.6
Requires-Dist: psycopg2
Requires-Dist: pandas
Requires-Dist: astropy
